README.rst
setup.py
scikit_reflectometry.egg-info/PKG-INFO
scikit_reflectometry.egg-info/SOURCES.txt
scikit_reflectometry.egg-info/dependency_links.txt
scikit_reflectometry.egg-info/requires.txt
scikit_reflectometry.egg-info/top_level.txt
skreflectometry/__init__.py
skreflectometry/setup.py
skreflectometry/stuff.py
skreflectometry/version.py
skreflectometry/tests/__init__.py
skreflectometry/tests/test_stuff.py
skreflectometry/tests/test_version.py