Metadata-Version: 1.1
Name: scikit-reflectometry
Version: 0.1
Summary: Scikit Reflectometry package
Home-page: https://github.com/OpenReflectometry/scikit-reflectometry
Author: ('Diogo Aguiam',)
Author-email: daguiam@ipfn.tecnico.ulisboa.pt
License: BSD
Download-URL: https://github.com/OpenReflectometry/scikit-reflectometry
Platform: UNKNOWN
Classifier: Development Status :: 1 - Planning
Classifier: Intended Audience :: Developers
Classifier: Intended Audience :: Science/Research
Classifier: License :: OSI Approved :: BSD License
Classifier: Topic :: Scientific/Engineering
